PDFknife/A5.py
PDFknife/__init__.py
PDFknife/_utils.py
PDFknife/cut.py
PDFknife/engine.py
PDFknife/even.py
PDFknife/extract.py
PDFknife/merge.py
PDFknife/reverse.py
PDFknife/shrink.py
PDFknife/split.py
PDFknife/tearpages.py
PDFknife/trim.py
PDFknife-0.2.4.data/scripts/pdfknife-A5.py
PDFknife-0.2.4.data/scripts/pdfknife-cut.py
PDFknife-0.2.4.data/scripts/pdfknife-even.py
PDFknife-0.2.4.data/scripts/pdfknife-extract.py
PDFknife-0.2.4.data/scripts/pdfknife-merge.py
PDFknife-0.2.4.data/scripts/pdfknife-recto.py
PDFknife-0.2.4.data/scripts/pdfknife-reverse.py
PDFknife-0.2.4.data/scripts/pdfknife-shrink.py
PDFknife-0.2.4.data/scripts/pdfknife-split.py
PDFknife-0.2.4.data/scripts/pdfknife-tearpages.py
PDFknife-0.2.4.data/scripts/pdfknife-trim.py
PDFknife-0.2.4.dist-info/LICENSE
PDFknife-0.2.4.dist-info/METADATA
PDFknife-0.2.4.dist-info/WHEEL
PDFknife-0.2.4.dist-info/top_level.txt
PDFknife-0.2.4.dist-info/RECORD
