Metadata-Version: 2.1
Name: PDFknife
Version: 0.2.4
Summary: Command line tools to manipulate PDF files
Home-page: https://github.com/sciunto-org/PDFknife
Author: Francois Boulogne
Author-email: devel@sciunto.org
License: BSD
License-File: LICENSE
Requires-Dist: PyPDF2 >=3.0.0
Requires-Dist: setuptools
